devloop/__init__.py
devloop/agents/__init__.py
devloop/agents/agent_health_monitor.py
devloop/agents/ci_monitor.py
devloop/agents/code_rabbit.py
devloop/agents/doc_lifecycle.py
devloop/agents/echo.py
devloop/agents/file_logger.py
devloop/agents/formatter.py
devloop/agents/git_commit_assistant.py
devloop/agents/linter.py
devloop/agents/performance_profiler.py
devloop/agents/sandbox_helper.py
devloop/agents/security_scanner.py
devloop/agents/snyk.py
devloop/agents/test_runner.py
devloop/agents/type_checker.py
devloop/cli/__init__.py
devloop/cli/agent_rules.py
devloop/cli/coderabbit_installer.py
devloop/cli/commands/__init__.py
devloop/cli/commands/agent_publish.py
devloop/cli/commands/audit.py
devloop/cli/commands/custom_agents.py
devloop/cli/commands/feedback.py
devloop/cli/commands/marketplace.py
devloop/cli/commands/marketplace_server.py
devloop/cli/commands/metrics.py
devloop/cli/commands/release.py
devloop/cli/commands/summary.py
devloop/cli/commands/telemetry.py
devloop/cli/commands/tools.py
devloop/cli/main.py
devloop/cli/main_v1.py
devloop/cli/pre_push_check.py
devloop/cli/prerequisites.py
devloop/cli/pyodide_installer.py
devloop/cli/snyk_installer.py
devloop/cli/templates/.devloop/tools-registry.json
devloop/cli/templates/claude_commands/README.md
devloop/cli/templates/claude_commands/agent-summary.md
devloop/cli/templates/claude_commands/devloop-findings.md
devloop/cli/templates/claude_commands/devloop-status.md
devloop/cli/templates/claude_commands/extract-findings.md
devloop/cli/templates/claude_commands/verify-work.md
devloop/cli/templates/devloop_agents_template.md
devloop/cli/templates/git_hooks/post-commit
devloop/cli/templates/git_hooks/pre-commit
devloop/cli/templates/git_hooks/pre-commit-checks
devloop/cli/templates/git_hooks/pre-push
devloop/cli/templates/supervisor/devloop.conf
devloop/cli/templates/systemd/devloop.service
devloop/collectors/__init__.py
devloop/collectors/base.py
devloop/collectors/filesystem.py
devloop/collectors/git.py
devloop-0.7.0.dist-info/METADATA
devloop-0.7.0.dist-info/WHEEL
devloop-0.7.0.dist-info/entry_points.txt
devloop-0.7.0.dist-info/licenses/LICENSE
devloop-0.7.0.dist-info/RECORD
