Metadata-Version: 2.4
Name: devloop
Version: 0.7.0
Summary: Intelligent background agents for development workflow automation
License: MIT
License-File: LICENSE
Keywords: agents,development,automation,code-quality,testing,linting,security,continuous-integration,devops
Author: DevLoop Contributors
Author-email: devloop@example.com
Requires-Python: >=3.11,<4.0
Classifier: Development Status :: 4 - Beta
Classifier: Intended Audience :: Developers
Classifier: License :: OSI Approved :: MIT License
Classifier: Operating System :: OS Independent
Classifier: Programming Language :: Python :: 3
Classifier: Programming Language :: Python :: 3.11
Classifier: Programming Language :: Python :: 3.12
Classifier: Programming Language :: Python :: 3.13
Classifier: Programming Language :: Python :: 3.14
Classifier: Topic :: Software Development :: Build Tools
Classifier: Topic :: Software Development :: Libraries :: Python Modules
Classifier: Topic :: Software Development :: Quality Assurance
Classifier: Topic :: Utilities
Provides-Extra: all-optional
Provides-Extra: ci-monitor
Provides-Extra: code-rabbit
Provides-Extra: marketplace-api
Provides-Extra: snyk
Requires-Dist: aiofiles (>=23.2,<24.0)
Requires-Dist: lsprotocol (>=2023.0.0,<2024.0.0)
Requires-Dist: psutil (>=5.9,<6.0)
Requires-Dist: pydantic (>=2.5,<3.0)
Requires-Dist: pygls (>=1.3.0,<2.0.0)
Requires-Dist: rich (>=13.7,<14.0)
Requires-Dist: typer (>=0.15,<1.0)
Requires-Dist: watchdog (>=3.0,<4.0)
Project-URL: Documentation, https://github.com/wioota/devloop#readme
Project-URL: Homepage, https://github.com/wioota/devloop
Project-URL: Repository, https://github.com/wioota/devloop
